drdev/__init__.py
drdev/__version__.py
drdev/cli/__init__.py
drdev/cli/drdev.py
drdev-0.1.0.dist-info/LICENSE
drdev-0.1.0.dist-info/METADATA
drdev-0.1.0.dist-info/WHEEL
drdev-0.1.0.dist-info/entry_points.txt
drdev-0.1.0.dist-info/top_level.txt
drdev-0.1.0.dist-info/RECORD
